git_credential_op/__init__.py
git_credential_op/__main__.py
git_credential_op/cli.py
git_credential_op-0.1.0.dist-info/WHEEL
git_credential_op-0.1.0.dist-info/entry_points.txt
git_credential_op-0.1.0.dist-info/METADATA
git_credential_op-0.1.0.dist-info/RECORD
