Metadata-Version: 2.4
Name: git-credential-op
Version: 0.1.0
Summary: A simple `git credential` helper for 1password CLI (op)
Author: Nicholas Hurley
License-Expression: CC0-1.0
Requires-Dist: click
Requires-Python: >=3.13
Project-URL: CI, https://builds.sr.ht/nwgh/git-credential-op
Project-URL: Changelog, https://git.sr.ht/~nwgh/git-credential-op/log
Project-URL: Homepage, https://sr.ht/~nwgh/git-credential-op
Project-URL: Issues, https://todo.sr.ht/~nwgh/git-credential-op
